<annotation>
	<folder>VOC2007_pottedplant</folder>
	<filename>001443.jpg</filename>
	<size>
		<width>480</width>
		<height>318</height>
		<depth>3</depth>
	</size>
	<object>
		<name>car</name>
		<pose>Unspecified</pose>
		<truncated>0</truncated>
		<difficult>0</difficult>
		<bndbox>
			<xmin>131</xmin>
			<ymin>93</ymin>
			<xmax>345</xmax>
			<ymax>206</ymax>
		</bndbox>
	</object>
	<object>
		<name>horse</name>
		<pose>Left</pose>
		<truncated>0</truncated>
		<difficult>0</difficult>
		<bndbox>
			<xmin>138</xmin>
			<ymin>93</ymin>
			<xmax>397</xmax>
			<ymax>289</ymax>
		</bndbox>
	</object>
	<object>
		<name>pottedplant</name>
		<pose>Unspecified</pose>
		<truncated>0</truncated>
		<difficult>0</difficult>
		<bndbox>
			<xmin>182</xmin>
			<ymin>57</ymin>
			<xmax>251</xmax>
			<ymax>196</ymax>
		</bndbox>
	</object>
</annotation>