<annotation>
	<folder>VOC2007_pottedplant</folder>
	<filename>002739.jpg</filename>
	<size>
		<width>500</width>
		<height>330</height>
		<depth>3</depth>
	</size>
	<object>
		<name>bicycle</name>
		<pose>Unspecified</pose>
		<truncated>0</truncated>
		<difficult>0</difficult>
		<bndbox>
			<xmin>214</xmin>
			<ymin>143</ymin>
			<xmax>424</xmax>
			<ymax>315</ymax>
		</bndbox>
	</object>
	<object>
		<name>person</name>
		<pose>Unspecified</pose>
		<truncated>0</truncated>
		<difficult>0</difficult>
		<bndbox>
			<xmin>217</xmin>
			<ymin>38</ymin>
			<xmax>398</xmax>
			<ymax>282</ymax>
		</bndbox>
	</object>
	<object>
		<name>person</name>
		<pose>Unspecified</pose>
		<truncated>0</truncated>
		<difficult>1</difficult>
		<bndbox>
			<xmin>76</xmin>
			<ymin>124</ymin>
			<xmax>96</xmax>
			<ymax>171</ymax>
		</bndbox>
	</object>
	<object>
		<name>pottedplant</name>
		<pose>Unspecified</pose>
		<truncated>0</truncated>
		<difficult>1</difficult>
		<bndbox>
			<xmin>88</xmin>
			<ymin>108</ymin>
			<xmax>109</xmax>
			<ymax>174</ymax>
		</bndbox>
	</object>
</annotation>