<annotation>
	<folder>VOC2007_cats</folder>
	<filename>000085.jpg</filename>
	<size>
		<width>500</width>
		<height>375</height>
		<depth>3</depth>
	</size>
	<object>
		<name>cat</name>
		<pose>Rear</pose>
		<truncated>0</truncated>
		<difficult>0</difficult>
		<bndbox>
			<xmin>289</xmin>
			<ymin>106</ymin>
			<xmax>338</xmax>
			<ymax>192</ymax>
		</bndbox>
	</object>
	<object>
		<name>boat</name>
		<pose>Rear</pose>
		<truncated>0</truncated>
		<difficult>0</difficult>
		<bndbox>
			<xmin>375</xmin>
			<ymin>144</ymin>
			<xmax>403</xmax>
			<ymax>188</ymax>
		</bndbox>
	</object>
	<object>
		<name>boat</name>
		<pose>Rear</pose>
		<truncated>0</truncated>
		<difficult>0</difficult>
		<bndbox>
			<xmin>458</xmin>
			<ymin>154</ymin>
			<xmax>480</xmax>
			<ymax>190</ymax>
		</bndbox>
	</object>
	<object>
		<name>boat</name>
		<pose>Unspecified</pose>
		<truncated>1</truncated>
		<difficult>0</difficult>
		<bndbox>
			<xmin>2</xmin>
			<ymin>1</ymin>
			<xmax>312</xmax>
			<ymax>375</ymax>
		</bndbox>
	</object>
</annotation>