<annotation>
	<folder>VOC2007_cats</folder>
	<filename>001304.jpg</filename>
	<size>
		<width>500</width>
		<height>375</height>
		<depth>3</depth>
	</size>
	<object>
		<name>bus</name>
		<pose>Frontal</pose>
		<truncated>0</truncated>
		<difficult>0</difficult>
		<bndbox>
			<xmin>281</xmin>
			<ymin>295</ymin>
			<xmax>338</xmax>
			<ymax>354</ymax>
		</bndbox>
	</object>
	<object>
		<name>cat</name>
		<pose>Unspecified</pose>
		<truncated>1</truncated>
		<difficult>1</difficult>
		<bndbox>
			<xmin>335</xmin>
			<ymin>315</ymin>
			<xmax>357</xmax>
			<ymax>337</ymax>
		</bndbox>
	</object>
</annotation>