<annotation>
	<folder>VOC2007_cats</folder>
	<filename>002623.jpg</filename>
	<size>
		<width>500</width>
		<height>375</height>
		<depth>3</depth>
	</size>
	<object>
		<name>cat</name>
		<pose>Right</pose>
		<truncated>0</truncated>
		<difficult>0</difficult>
		<bndbox>
			<xmin>58</xmin>
			<ymin>192</ymin>
			<xmax>281</xmax>
			<ymax>277</ymax>
		</bndbox>
	</object>
	<object>
		<name>boat</name>
		<pose>Left</pose>
		<truncated>0</truncated>
		<difficult>0</difficult>
		<bndbox>
			<xmin>210</xmin>
			<ymin>72</ymin>
			<xmax>334</xmax>
			<ymax>237</ymax>
		</bndbox>
	</object>
	<object>
		<name>boat</name>
		<pose>Right</pose>
		<truncated>0</truncated>
		<difficult>0</difficult>
		<bndbox>
			<xmin>314</xmin>
			<ymin>194</ymin>
			<xmax>413</xmax>
			<ymax>230</ymax>
		</bndbox>
	</object>
</annotation>