<annotation>
	<folder>VOC2007_cats</folder>
	<filename>002794.jpg</filename>
	<size>
		<width>500</width>
		<height>375</height>
		<depth>3</depth>
	</size>
	<object>
		<name>cow</name>
		<pose>Frontal</pose>
		<truncated>0</truncated>
		<difficult>0</difficult>
		<bndbox>
			<xmin>244</xmin>
			<ymin>130</ymin>
			<xmax>404</xmax>
			<ymax>375</ymax>
		</bndbox>
	</object>
	<object>
		<name>cat</name>
		<pose>Unspecified</pose>
		<truncated>0</truncated>
		<difficult>0</difficult>
		<bndbox>
			<xmin>69</xmin>
			<ymin>73</ymin>
			<xmax>205</xmax>
			<ymax>153</ymax>
		</bndbox>
	</object>
</annotation>