<annotation>
	<folder>VOC2007_cats</folder>
	<filename>003248.jpg</filename>
	<size>
		<width>500</width>
		<height>375</height>
		<depth>3</depth>
	</size>
	<object>
		<name>car</name>
		<pose>Frontal</pose>
		<truncated>0</truncated>
		<difficult>0</difficult>
		<bndbox>
			<xmin>149</xmin>
			<ymin>112</ymin>
			<xmax>418</xmax>
			<ymax>300</ymax>
		</bndbox>
	</object>
	<object>
		<name>cat</name>
		<pose>Left</pose>
		<truncated>1</truncated>
		<difficult>0</difficult>
		<bndbox>
			<xmin>1</xmin>
			<ymin>147</ymin>
			<xmax>172</xmax>
			<ymax>230</ymax>
		</bndbox>
	</object>
</annotation>